fastapi_quickcrud/__init__.py
fastapi_quickcrud/crud_router.py
fastapi_quickcrud/misc/__init__.py
fastapi_quickcrud/misc/abstract_execute.py
fastapi_quickcrud/misc/abstract_parser.py
fastapi_quickcrud/misc/abstract_query.py
fastapi_quickcrud/misc/abstract_route.py
fastapi_quickcrud/misc/covert_model.py
fastapi_quickcrud/misc/crud_model.py
fastapi_quickcrud/misc/exceptions.py
fastapi_quickcrud/misc/memory_sql.py
fastapi_quickcrud/misc/schema_builder.py
fastapi_quickcrud/misc/type.py
fastapi_quickcrud/misc/utils.py
fastapi_quickcrud-0.2.8.dist-info/LICENSE
fastapi_quickcrud-0.2.8.dist-info/METADATA
fastapi_quickcrud-0.2.8.dist-info/WHEEL
fastapi_quickcrud-0.2.8.dist-info/top_level.txt
fastapi_quickcrud-0.2.8.dist-info/RECORD
