Metadata-Version: 2.1
Name: fastapi-quickcrud
Version: 0.2.8
Summary: A comprehensive FastaAPI's CRUD router generator for SQLALchemy.
Home-page: https://github.com/LuisLuii/FastAPIQuickCRUD
Author: Luis Lui
Author-email: luis11235178@gmail.com
License: MIT License
Keywords: fastapi,crud,restful,routing,SQLAlchemy,generator,crudrouter,postgresql,builder
Classifier: Operating System :: OS Independent
Classifier: Programming Language :: Python :: 3
Classifier: Programming Language :: Python
Classifier: Topic :: Internet
Classifier: Topic :: Software Development :: Libraries :: Application Frameworks
Classifier: Topic :: Software Development :: Libraries :: Python Modules
Classifier: Topic :: Software Development :: Libraries
Classifier: Topic :: Software Development :: Code Generators
Classifier: Topic :: Software Development
Classifier: Typing :: Typed
Classifier: Development Status :: 5 - Production/Stable
Classifier: Environment :: Web Environment
Classifier: Framework :: AsyncIO
Classifier: Intended Audience :: Developers
Classifier: Intended Audience :: Information Technology
Classifier: Intended Audience :: System Administrators
Classifier: License :: OSI Approved :: MIT License
Classifier: Programming Language :: Python :: 3 :: Only
Classifier: Programming Language :: Python :: 3.7
Classifier: Programming Language :: Python :: 3.8
Classifier: Programming Language :: Python :: 3.9
Classifier: Programming Language :: Python :: 3.10
Classifier: Topic :: Internet :: WWW/HTTP :: HTTP Servers
Classifier: Topic :: Internet :: WWW/HTTP
Requires-Python: >=3.7
License-File: LICENSE
Requires-Dist: fastapi ==0.68.2
Requires-Dist: pydantic ==1.8.2
Requires-Dist: SQLAlchemy ==1.4.30
Requires-Dist: StrEnum ==0.4.7
Requires-Dist: starlette ==0.14.2
Requires-Dist: aiosqlite ==0.17.0
Provides-Extra: dev
Requires-Dist: uvicorn ==0.17.0 ; extra == 'dev'
Requires-Dist: greenlet ==1.1.2 ; extra == 'dev'
Requires-Dist: anyio ==3.5.0 ; extra == 'dev'
